denoise_fmri/__init__.py
denoise_fmri/run.py
denoise_fmri/config/snakebids.yml
denoise_fmri/resources/dataset_description.json
denoise_fmri/workflow/Snakefile
denoise_fmri/workflow/scripts/denoise.py
denoise_fmri/workflow/scripts/smooth.py
denoise_fmri-0.1.0.dist-info/METADATA
denoise_fmri-0.1.0.dist-info/WHEEL
denoise_fmri-0.1.0.dist-info/entry_points.txt
denoise_fmri-0.1.0.dist-info/top_level.txt
denoise_fmri-0.1.0.dist-info/RECORD
